[{"id":"6285731261728@s.whatsapp.net","limit":11},{"id":"6285797918433@s.whatsapp.net","limit":5},{"id":"6282140801090@s.whatsapp.net","limit":2},{"id":"17706916497@s.whatsapp.net","limit":1},{"id":"6283106880085@s.whatsapp.net","limit":4},{"id":"6285394518447@s.whatsapp.net","limit":0},{"id":"6281262646003@s.whatsapp.net","limit":3},{"id":"6281327433143@s.whatsapp.net","limit":1},{"id":"6287820483329@s.whatsapp.net","limit":8},{"id":"6281284917809@s.whatsapp.net","limit":3},{"id":"6282251927141@s.whatsapp.net","limit":5},{"id":"6287784728759@s.whatsapp.net","limit":5},{"id":"6289628038275@s.whatsapp.net","limit":0},{"id":"6283141101338@s.whatsapp.net","limit":0},{"id":"6283117523838@s.whatsapp.net","limit":5},{"id":"48699558469@s.whatsapp.net","limit":5},{"id":"6287872221225@s.whatsapp.net","limit":0},{"id":"6282161874005@s.whatsapp.net","limit":8},{"id":"62895333575151@s.whatsapp.net","limit":5},{"id":"6285857948496@s.whatsapp.net","limit":2},{"id":"6287893478735@s.whatsapp.net","limit":0},{"id":"6288258298467@s.whatsapp.net","limit":11},{"id":"6287850082169@s.whatsapp.net","limit":0},{"id":"62887426379507@s.whatsapp.net","limit":4},{"id":"6283869049179@s.whatsapp.net","limit":5},{"id":"6289529509568@s.whatsapp.net","limit":5},{"id":"6281211314913@s.whatsapp.net","limit":5},{"id":"6281212198049@s.whatsapp.net","limit":8},{"id":"6285768445635@s.whatsapp.net","limit":2},{"id":"6285664770042@s.whatsapp.net","limit":4}]